{
  "context": {},
  "ext": {},
  "result": [
    {
      "pics": "https://img.alicdn.com/bao/uploaded///img.alicdn.com/i2/3495866263/O1CN01vFAkhq1w8V6hlCysk_!!3495866263.jpg",
      "price": "6550.00",
      "productTitle": "湖南张家界旅游6天跟团游韶山玻璃桥天门山黄龙洞凤凰古城送表演",
      "presellPrice": null,
      "preSaleCount": null,
      "discountPrice": "2620.00",
      "seller": 0,
      "href": "https://items.fliggy.com/item.htm?id=598824649278&t_trace_id=null&scm=20140635.1_1_88.0.0b51191815731020373405283e65af",
      "city": "张家界",
      "tagList": [
        {
          "text": "",
          "icon": "//img.alicdn.com/tfs/TB1YjZ3g9f2gK0jSZFPXXXsopXa-256-40.png",
          "borderColor": null,
          "textColor": null,
          "bgColor": null,
          "pormotion": false,
          "className": null
        },
        {
          "text": "飞猪红包",
          "icon": "//img.alicdn.com/tfs/TB1BYk4gYr1gK0jSZR0XXbP8XXa-134-40.png",
          "borderColor": "#FF0036",
          "textColor": "#FF0036",
          "bgColor": "#FFEFF2",
          "pormotion": false,
          "className": null
        },
        {
          "text": "纯玩",
          "icon": null,
          "borderColor": "#DDDDDD",
          "textColor": "#999999",
          "bgColor": null,
          "pormotion": false,
          "className": null
        }
      ],
      "titleTagList": []
    },
    {
      "pics": "https://img.alicdn.com/bao/uploaded///img.alicdn.com/i5/TB1GgI7dHr1gK0jSZFD7v69yVXa_045244.jpg",
      "price": "138.00",
      "productTitle": "陕西西安旅游兵马俑一日游纯玩华清池长恨歌骊山一日游可选15人团",
      "presellPrice": null,
      "preSaleCount": null,
      "discountPrice": "138.00",
      "seller": 1693,
      "href": "https://items.fliggy.com/item.htm?id=592301871774&t_trace_id=null&scm=20140635.1_1_79.0.0b51191815731020373405283e65af",
      "city": "西安",
      "tagList": [
        {
          "text": "纯玩",
          "icon": null,
          "borderColor": "#DDDDDD",
          "textColor": "#999999",
          "bgColor": null,
          "pormotion": false,
          "className": null
        },
        {
          "text": "明日可用",
          "icon": null,
          "borderColor": "#DDDDDD",
          "textColor": "#999999",
          "bgColor": null,
          "pormotion": false,
          "className": null
        }
      ],
      "titleTagList": []
    },
    {
      "pics": "https://img.alicdn.com/bao/uploaded///img.alicdn.com/i4/3503893379/O1CN016d0lN21apcoaylDiV_!!3503893379.jpg",
      "price": "2575.00",
      "productTitle": "湖南旅游 张家界6天5晚跟团游玻璃桥天门山凤凰古城 飞猪长沙旅行",
      "presellPrice": null,
      "preSaleCount": null,
      "discountPrice": "2060.00",
      "seller": 0,
      "href": "https://items.fliggy.com/item.htm?id=573093311172&t_trace_id=null&scm=20140635.1_1_86.0.0b51191815731020373405283e65af",
      "city": "张家界",
      "tagList": [
        {
          "text": "",
          "icon": "//img.alicdn.com/tfs/TB1YjZ3g9f2gK0jSZFPXXXsopXa-256-40.png",
          "borderColor": null,
          "textColor": null,
          "bgColor": null,
          "pormotion": false,
          "className": null
        },
        {
          "text": "飞猪红包",
          "icon": "//img.alicdn.com/tfs/TB1BYk4gYr1gK0jSZR0XXbP8XXa-134-40.png",
          "borderColor": "#FF0036",
          "textColor": "#FF0036",
          "bgColor": "#FFEFF2",
          "pormotion": false,
          "className": null
        },
        {
          "text": "纯玩",
          "icon": null,
          "borderColor": "#DDDDDD",
          "textColor": "#999999",
          "bgColor": null,
          "pormotion": false,
          "className": null
        }
      ],
      "titleTagList": []
    },
    {
      "pics": "https://img.alicdn.com/bao/uploaded///img.alicdn.com/i2/3518932406/O1CN01j1ujNx1TdzSYSkiJW_!!3518932406.jpg",
      "price": "1888.00",
      "productTitle": "飞猪专线｜高铁往返张家界旅游纯玩4天3晚跟团游玻璃桥天门山凤凰",
      "presellPrice": null,
      "preSaleCount": null,
      "discountPrice": "1888.00",
      "seller": 52,
      "href": "https://items.fliggy.com/item.htm?id=561670752500&t_trace_id=null&scm=20140635.1_1_2.0.0b51191815731020373405283e65af",
      "city": "张家界",
      "tagList": [
        {
          "text": "飞猪红包",
          "icon": "//img.alicdn.com/tfs/TB1BYk4gYr1gK0jSZR0XXbP8XXa-134-40.png",
          "borderColor": "#FF0036",
          "textColor": "#FF0036",
          "bgColor": "#FFEFF2",
          "pormotion": false,
          "className": null
        },
        {
          "text": "飞猪专线",
          "icon": "//gw.alicdn.com/tfs/TB1lAjhfuuSBuNjy1XcXXcYjFXa-98-32.png",
          "borderColor": "#DDDDDD",
          "textColor": "#FAFAFA",
          "bgColor": null,
          "pormotion": false,
          "className": null
        },
        {
          "text": "纯玩",
          "icon": null,
          "borderColor": "#DDDDDD",
          "textColor": "#999999",
          "bgColor": null,
          "pormotion": false,
          "className": null
        }
      ],
      "titleTagList": []
    },
    {
      "pics": "https://img.alicdn.com/bao/uploaded///img.alicdn.com/i2/4162896728/O1CN01hJwVac1zZTFEdV1xs_!!4162896728.jpg",
      "price": "1850.00",
      "productTitle": "西安旅游 西安五天四晚跟团游兵马俑华山  听青曲社纯玩含机票",
      "presellPrice": null,
      "preSaleCount": null,
      "discountPrice": "1850.00",
      "seller": 104,
      "href": "https://items.fliggy.com/item.htm?id=590875057767&t_trace_id=null&scm=20140635.1_1_8.0.0b51191815731020373405283e65af",
      "city": "西安",
      "tagList": [
        {
          "text": "",
          "icon": "//img.alicdn.com/tfs/TB1YjZ3g9f2gK0jSZFPXXXsopXa-256-40.png",
          "borderColor": null,
          "textColor": null,
          "bgColor": null,
          "pormotion": false,
          "className": null
        },
        {
          "text": "飞猪红包",
          "icon": "//img.alicdn.com/tfs/TB1BYk4gYr1gK0jSZR0XXbP8XXa-134-40.png",
          "borderColor": "#FF0036",
          "textColor": "#FF0036",
          "bgColor": "#FFEFF2",
          "pormotion": false,
          "className": null
        },
        {
          "text": "纯玩",
          "icon": null,
          "borderColor": "#DDDDDD",
          "textColor": "#999999",
          "bgColor": null,
          "pormotion": false,
          "className": null
        }
      ],
      "titleTagList": []
    },
    {
      "pics": "https://img.alicdn.com/bao/uploaded///img.alicdn.com/i1/2200783063853/O1CN01LHRsUw1eKia6J18Pf_!!2200783063853.jpg",
      "price": "2110.00",
      "productTitle": "湖南张家界旅游5天4晚跟团游 长沙湘西凤凰古城天门山五日跟团游",
      "presellPrice": null,
      "preSaleCount": null,
      "discountPrice": "2110.00",
      "seller": 6,
      "href": "https://items.fliggy.com/item.htm?id=597254244030&t_trace_id=null&scm=20140635.1_1_78.0.0b51191815731020373405283e65af",
      "city": "张家界",
      "tagList": [
        {
          "text": "",
          "icon": "//img.alicdn.com/tfs/TB1YjZ3g9f2gK0jSZFPXXXsopXa-256-40.png",
          "borderColor": null,
          "textColor": null,
          "bgColor": null,
          "pormotion": false,
          "className": null
        },
        {
          "text": "即时确认",
          "icon": null,
          "borderColor": "#DDDDDD",
          "textColor": "#999999",
          "bgColor": null,
          "pormotion": false,
          "className": null
        }
      ],
      "titleTagList": []
    },
    {
      "pics": "https://img.alicdn.com/bao/uploaded///img.alicdn.com/i3/2201299787015/O1CN01UWAQ9W21guvt2QEjR_!!2201299787015.jpg",
      "price": "3120.00",
      "productTitle": "全国出发贵州旅游5天4晚直飞纯玩黄果树瀑布荔波大小七孔西江千户",
      "presellPrice": null,
      "preSaleCount": null,
      "discountPrice": "3120.00",
      "seller": 0,
      "href": "https://items.fliggy.com/item.htm?id=594911224251&t_trace_id=null&scm=20140635.1_1_70.0.0b51191815731020373405283e65af",
      "city": "成都",
      "tagList": [
        {
          "text": "纯玩",
          "icon": null,
          "borderColor": "#DDDDDD",
          "textColor": "#999999",
          "bgColor": null,
          "pormotion": false,
          "className": null
        }
      ],
      "titleTagList": []
    },
    {
      "pics": "https://img.alicdn.com/bao/uploaded///img.alicdn.com/i2/2206456918555/O1CN017LcGMG2D4Eu9Jr756_!!2206456918555.jpg",
      "price": "1180.00",
      "productTitle": "高铁往返湖南长沙张家界4天3晚玻璃桥天门山凤凰古城纯玩旅游跟团",
      "presellPrice": null,
      "preSaleCount": null,
      "discountPrice": "1180.00",
      "seller": 49,
      "href": "https://items.fliggy.com/item.htm?id=602666168093&t_trace_id=null&scm=20140635.1_1_25.0.0b51191815731020373405283e65af",
      "city": "张家界",
      "tagList": [
        {
          "text": "",
          "icon": "//img.alicdn.com/tfs/TB1YjZ3g9f2gK0jSZFPXXXsopXa-256-40.png",
          "borderColor": null,
          "textColor": null,
          "bgColor": null,
          "pormotion": false,
          "className": null
        },
        {
          "text": "纯玩",
          "icon": null,
          "borderColor": "#DDDDDD",
          "textColor": "#999999",
          "bgColor": null,
          "pormotion": false,
          "className": null
        },
        {
          "text": "即时确认",
          "icon": null,
          "borderColor": "#DDDDDD",
          "textColor": "#999999",
          "bgColor": null,
          "pormotion": false,
          "className": null
        }
      ],
      "titleTagList": []
    }
  ],
  "success": true,
  "version": "1.0",
  "userId": null,
  "tId": "uXpFFhKd/AUCAbZq1JbSkmj+",
  "ip": "127.0.0.1",
  "uid": null,
  "tdsid": "10073",
  "appName": "travelnode",
  "pageSize": "8",
  "channelId": "30004",
  "destName": "西安,张家界,凤凰"
}